graia/ariadne/__init__.py
graia/ariadne/app.py
graia/ariadne/connection/__init__.py
graia/ariadne/connection/_info.py
graia/ariadne/connection/config.py
graia/ariadne/connection/http.py
graia/ariadne/connection/util.py
graia/ariadne/connection/ws.py
graia/ariadne/console/__init__.py
graia/ariadne/console/saya.py
graia/ariadne/context.py
graia/ariadne/dispatcher.py
graia/ariadne/entry/__init__.py
graia/ariadne/entry/broadcast.py
graia/ariadne/entry/event.py
graia/ariadne/entry/message.py
graia/ariadne/entry/saya.py
graia/ariadne/entry/scheduler.py
graia/ariadne/event/__init__.py
graia/ariadne/event/lifecycle.py
graia/ariadne/event/message.py
graia/ariadne/event/mirai.py
graia/ariadne/exception.py
graia/ariadne/message/__init__.py
graia/ariadne/message/chain.py
graia/ariadne/message/commander/__init__.py
graia/ariadne/message/commander/creart.py
graia/ariadne/message/commander/saya.py
graia/ariadne/message/commander/util.py
graia/ariadne/message/element.py
graia/ariadne/message/formatter.py
graia/ariadne/message/parser/__init__.py
graia/ariadne/message/parser/base.py
graia/ariadne/message/parser/twilight.py
graia/ariadne/message/parser/util.py
graia/ariadne/model/__init__.py
graia/ariadne/model/relationship.py
graia/ariadne/model/util.py
graia/ariadne/py.typed
graia/ariadne/service.py
graia/ariadne/typing.py
graia/ariadne/util/__init__.py
graia/ariadne/util/async_exec.py
graia/ariadne/util/cooldown.py
graia/ariadne/util/interrupt.py
graia/ariadne/util/saya.py
graia/ariadne/util/send.py
graia/ariadne/util/validator.py
graia_ariadne-0.7.16.dist-info/entry_points.txt
graia_ariadne-0.7.16.dist-info/LICENSE
graia_ariadne-0.7.16.dist-info/WHEEL
graia_ariadne-0.7.16.dist-info/METADATA
graia_ariadne-0.7.16.dist-info/RECORD
