Metadata-Version: 2.1
Name: graia-ariadne
Version: 0.7.16
Summary: Another elegant Python QQ Bot framework for mirai and mirai-api-http v2.
Home-page: https://github.com/GraiaProject/Ariadne
Keywords: graia,bot,qq,framework,mirai,ariadne
Author: BlueGlassBlock
Author-email: blueglassblock@outlook.com
Requires-Python: >=3.8,<4.0
Classifier: Development Status :: 4 - Beta
Classifier: Framework :: AsyncIO
Classifier: Framework :: Robot Framework :: Library
Classifier: Operating System :: OS Independent
Classifier: Programming Language :: Python :: 3
Classifier: Programming Language :: Python :: 3.10
Classifier: Programming Language :: Python :: 3.8
Classifier: Programming Language :: Python :: 3.9
Classifier: Topic :: Communications :: Chat
Classifier: Typing :: Typed
Provides-Extra: alconna
Provides-Extra: fastapi
Provides-Extra: full
Provides-Extra: graia
Provides-Extra: standard
Requires-Dist: aiohttp (>=3.7.4,<4.0.0)
Requires-Dist: arclet-alconna-graia; extra == "alconna" or extra == "full"
Requires-Dist: creart-graia (>=0.1.4,<0.2.0)
Requires-Dist: fastapi (>=0.74.1,<1.0.0); extra == "fastapi"
Requires-Dist: graia-amnesia (>=0.5.2,<0.6.0)
Requires-Dist: graia-broadcast (>=0.18.0,<0.19.0)
Requires-Dist: graia-saya (>=0.0,<0.1); extra == "graia" or extra == "standard" or extra == "full"
Requires-Dist: graia-scheduler (>=0.0,<0.1); extra == "graia" or extra == "standard" or extra == "full"
Requires-Dist: pydantic (>=1.8.2,<2.0.0)
Requires-Dist: richuru (>=0.1.0,<0.2.0); extra == "standard" or extra == "full"
Requires-Dist: typing-extensions (>=4.0,<5.0)
Requires-Dist: uvicorn[standard] (>=0.17.5,<0.18.0); extra == "fastapi"
Project-URL: Documentation, https://graia.readthedocs.io/projects/ariadne
Project-URL: Repository, https://github.com/GraiaProject/Ariadne
